multilevel_sabre/__init__.py
multilevel_sabre/clustering.py
multilevel_sabre/initial_embedding.py
multilevel_sabre/interpolation.py
multilevel_sabre/multilevel.py
multilevel_sabre/multilevel_sabre.py
multilevel_sabre/sabre.py
multilevel_sabre-0.1.1.dist-info/METADATA
multilevel_sabre-0.1.1.dist-info/WHEEL
multilevel_sabre-0.1.1.dist-info/top_level.txt
multilevel_sabre-0.1.1.dist-info/RECORD
