Metadata-Version: 2.4
Name: multilevel-sabre
Version: 0.1.1
Summary: A Qiskit transpiler pass implementing multi-level SABRE algorithm
Home-page: https://github.com/nks676/multilevel-sabre
Author: Naren Sathishkumar
Author-email: nks676@ucla.edu
Classifier: Programming Language :: Python :: 3
Classifier: License :: OSI Approved :: MIT License
Classifier: Operating System :: OS Independent
Requires-Python: >=3.10
Requires-Dist: qiskit>=1.4
Requires-Dist: networkx>=3.0
Requires-Dist: numpy>=1.20
Requires-Dist: scipy>=1.7
Dynamic: author
Dynamic: author-email
Dynamic: classifier
Dynamic: description
Dynamic: description-content-type
Dynamic: home-page
Dynamic: requires-dist
Dynamic: requires-python
Dynamic: summary
